<?xml version="1.0" encoding="UTF-8"?>
<persistence version="2.0"
	xmlns="http://java.sun.com/xml/ns/persistence" xmlns:xsi="http://www.w3.org/2001/XMLSchema-instance"
	xsi:schemaLocation="http://java.sun.com/xml/ns/persistence http://java.sun.com/xml/ns/persistence/persistence_2_0.xsd">
	<persistence-unit name="ApartmentManagementSoftware">
		<class>com.ams.sales.domain.model.bill.Bill</class>
		<class>com.ams.sales.domain.model.bill.BillItem</class>
		<class>com.ams.sales.domain.model.bill.BillPaymentRegister</class>
		<class>com.ams.sales.domain.model.bill.Payment</class>
		<class>com.ams.sales.domain.model.servicecatalog.Service</class>
		<class>com.ams.sales.domain.model.servicecatalog.ServiceCharge</class>
		<class>com.ams.sales.domain.model.servicecatalog.ServicePlan</class>
		<class>com.ams.sales.domain.model.servicecatalog.ServiceRate</class>
		<class>com.ams.sales.domain.model.servicecatalog.ServiceRateId</class>
		<class>com.ams.sales.domain.model.servicecatalog.ServiceSubscription</class>
		<class>com.ams.sales.domain.model.servicecatalog.ServiceUsage</class>
		<class>com.ams.finance.domain.model.Account</class>
		<class>com.ams.finance.domain.model.AccountDetail</class>
		<class>com.ams.finance.domain.model.Transaction</class>
		<class>com.ams.sharedkernel.domain.model.measuresandunits.Money</class>
		<class>com.ams.sharedkernel.domain.model.measuresandunits.Period</class>
		<class>com.ams.sharedkernel.domain.model.measuresandunits.Quantity</class>
		<class>com.ams.sharedkernel.domain.model.measuresandunits.Rate</class>
		<class>com.ams.usermanagement.domain.model.Address</class>
		<class>com.ams.usermanagement.domain.model.Person</class>
		<class>com.ams.usermanagement.domain.model.PersonDetail</class>
		<shared-cache-mode>ALL</shared-cache-mode>
		<properties>
			<property name="eclipselink.ddl-generation" value="drop-and-create-tables" />
			<property name="eclipselink.ddl-generation.output-mode"
				value="sql-script" />
			<property name="eclipselink.application-location" value="C:\Users\Moni\Desktop" />
		</properties>
	</persistence-unit>
</persistence>
